{
  "title": "پرسشنامه سنخ نمای مایرز- بریگز",
  "short_name": "MBTI",
  "description": {
    "overall": "سنخ نمای مایرز- بریگز یک پرسشنامه خودسنجی است که بر اساس نظریه تیپ‌های روان شناس و روانپزشک سویسی کارل گوستاو یونگ طراحی شده است. نتایج MBTI تفاوت‌های با ارزش ما بین انسان‌های طبیعی و سالم را مشخص می‌کند، تفاوت‌هایی که می‌تواند منبع و منشأ اکثر سوء تفاهم‌ها و اختلال‌های ارتباطاتی شود.",
    "purpose": "شناخت و درک تفاوت‌های شخصیت‌های سالم.",
    "applications": [
      "فهم بهتر خود و دیگران",
      "مشاوره ازدواج",
      "مشاوره شغلی",
      "کارمند یابی یا انتخاب مدیران",
      "ایجاد تیم‌های کاری",
      "آموزش و توسعه مدیریت و رهبری",
      "حل تعارضات درون سازمانی",
      "توسعه برنامه‌های درسی و آموزشی و تربیتی"
    ],
    "number_of_questions": 60
  },
  "response_scale": {
    "type": "انتخاب دوتایی (الف یا ب)",
    "options": [
      {
        "label": "الف"
      },
      {
        "label": "ب"
      }
    ],
    "instructions": "لطفا پاسخ مدنظر خود را با علامت یا X مشخص کنید."
  },
  "dimensions": [
    {
      "id": "EI",
      "name": "درون‌گرایی (I) / برون‌گرایی (E)",
      "description": "گرایش کلی در تمرکز توجه افراد."
    },
    {
      "id": "SN",
      "name": "حسی (S) / شهودی (N)",
      "description": "کارکرد و روشی که افراد اطلاعات کسب می‌کنند."
    },
    {
      "id": "TF",
      "name": "تفکری (T) / احساسی (F)",
      "description": "کارکرد و روشی که افراد از طریق آن تصمیم می‌گیرند."
    },
    {
      "id": "JP",
      "name": "منضبط (J) / ملاحظه‌کار (P)",
      "description": "گرایش خاصی که افراد سبک زندگی خود را با آن مشخص می‌کنند."
    }
  ],
  "questions": [
    {
      "id": 1,
      "text_a": "معمولاً احساسات و عواطف خود را در خویش نگه می‌دارم.",
      "text_b": "معمولاً احساسات و عواطف خود را با دیگران و به راحتی در میان می‌گذارم.",
      "dimension_mapping": {
        "a": "I",
        "b": "E"
      }
    },
    {
      "id": 2,
      "text_a": "امور قطعی و عینی مهم هستند.",
      "text_b": "نظریه‌ها مهم هستند.",
      "dimension_mapping": {
        "a": "S",
        "b": "N"
      }
    },
    {
      "id": 3,
      "text_a": "هنگام تصمیم‌گیری به آنچه که منطق و خرد بر آن حکم می‌کند، عمل می‌کنم.",
      "text_b": "هنگام تصمیم‌گیری به آنچه که عاطفه و دل به آن گواه می‌دهد، عمل می‌کنم.",
      "dimension_mapping": {
        "a": "T",
        "b": "F"
      }
    },
    {
      "id": 4,
      "text_a": "مایل هستم انعطاف‌پذیر باشم و در لحظه‌های آخر تصمیم بگیرم.",
      "text_b": "مایل هستم همه چیز برنامه‌ریزی شده باشد.",
      "dimension_mapping": {
        "a": "P",
        "b": "J"
      }
    },
    {
      "id": 5,
      "text_a": "کم ولی عمیق",
      "text_b": "زیاد ولی سطحی",
      "dimension_mapping": {
        "a": "I",
        "b": "E"
      }
    },
    {
      "id": 6,
      "text_a": "واقعیات عینی (آنچه وجود دارد) را مورد بررسی قرار می‌دهم.",
      "text_b": "حقایق (آنچه که باید وجود داشته باشد) را با قدرت تخیل خود مجسم می‌کنم.",
      "dimension_mapping": {
        "a": "S",
        "b": "N"
      }
    },
    {
      "id": 7,
      "text_a": "قاضی و داور عادل بهتر است.",
      "text_b": "معلم و مربی مهربان بهتر است.",
      "dimension_mapping": {
        "a": "T",
        "b": "F"
      }
    },
    {
      "id": 8,
      "text_a": "ترجیحاً ملاقات‌ها و دیدارهای خود را هرطور که پیش آید و بر اساس موقعیت آزادانه انجام می‌دهم.",
      "text_b": "ترجیحاً دیدار با افراد و وعده ملاقات را از پیش تعیین می‌کنم.",
      "dimension_mapping": {
        "a": "P",
        "b": "J"
      }
    },
    {
      "id": 9,
      "text_a": "کم حرف و محتاط هستم.",
      "text_b": "توجه دیگران را به خود جلب می‌کنم.",
      "dimension_mapping": {
        "a": "I",
        "b": "E"
      }
    },
    {
      "id": 10,
      "text_a": "اگر معلم بودم ترجیح می‌دادم دروسی را تدریس کنم که واقعیات و امور قطعی و عینی را شامل شوند.",
      "text_b": "اگر معلم بودم، ترجیحاً دروسی را تدریس می‌کردم که حقایق و نظریه‌ها و تئوری‌ها را شامل شوند.",
      "dimension_mapping": {
        "a": "S",
        "b": "N"
      }
    },
    {
      "id": 11,
      "text_a": "قاطع، محکم و استوار",
      "text_b": "انعطاف‌پذیر، ملایم و لطیف",
      "dimension_mapping": {
        "a": "T",
        "b": "F"
      }
    },
    {
      "id": 12,
      "text_a": "غالباً انجام کارهای پیش پا افتاده و جزئی را فراموش می‌کنم.",
      "text_b": "به منظور جلوگیری از فراموش شدن انجام کارها، آنها را یادداشت می‌کنم.",
      "dimension_mapping": {
        "a": "P",
        "b": "J"
      }
    },
    {
      "id": 13,
      "text_a": "در مهمانی‌ها، جلسات و گردهمایی‌ها منتظر می‌مانم تا دیگران به سوی من بیایند.",
      "text_b": "در مهمانی‌ها، جلسات و گردهمایی‌ها، من سر صحبت با دیگران را باز می‌کنم.",
      "dimension_mapping": {
        "a": "I",
        "b": "E"
      }
    },
    {
      "id": 14,
      "text_a": "گفتار مشروح و صریح",
      "text_b": "مفاهیم ادبی",
      "dimension_mapping": {
        "a": "S",
        "b": "N"
      }
    },
    {
      "id": 15,
      "text_a": "برنامه‌ریزی و آینده‌نگری",
      "text_b": "توجه کمتر به آینده",
      "dimension_mapping": {
        "a": "T",
        "b": "F"
      }
    },
    {
      "id": 16,
      "text_a": "معمولاً کارها را شروع می‌کنم و حین اجرا به رفع اشکالات اجرایی و تدارک مورد نیاز می‌پردازم.",
      "text_b": "قبل از اجرای طرح‌ها و کارها برنامه‌ریزی را انجام می‌دهم.",
      "dimension_mapping": {
        "a": "P",
        "b": "J"
      }
    },
    {
      "id": 17,
      "text_a": "دوستان کمتر ولی تماس بیشتر",
      "text_b": "دوستان بیشتر ولی تماس کمتر",
      "dimension_mapping": {
        "a": "I",
        "b": "E"
      }
    },
    {
      "id": 18,
      "text_a": "واقعی و مشخص",
      "text_b": "بر اساس قوه تخیل و ذوق",
      "dimension_mapping": {
        "a": "S",
        "b": "N"
      }
    },
    {
      "id": 19,
      "text_a": "منطق و دلیل",
      "text_b": "احساس و عاطفه",
      "dimension_mapping": {
        "a": "T",
        "b": "F"
      }
    },
    {
      "id": 20,
      "text_a": "در انجام کارهایی که از قبل پیش‌بینی نشده و یا فعالیت‌هایی که به سرعت و عکس‌العمل فوری نیاز دارند، موفق هستم.",
      "text_b": "در انجام کارهایی که بر اساس طرح و برنامه می‌باشد، موفق هستم.",
      "dimension_mapping": {
        "a": "P",
        "b": "J"
      }
    },
    {
      "id": 21,
      "text_a": "به طور معمول دوستان کمی داشته ولی روابط صمیمانه‌ای دارم.",
      "text_b": "به طور معمول با افراد زیادی دوستی و آشنایی دارم.",
      "dimension_mapping": {
        "a": "I",
        "b": "E"
      }
    },
    {
      "id": 22,
      "text_a": "به امور قطعی و مسلم و واقعیات جاری توجه دارم.",
      "text_b": "به پیش‌بینی اتفاقات و علل وقایع فکر می‌کنم.",
      "dimension_mapping": {
        "a": "S",
        "b": "N"
      }
    },
    {
      "id": 23,
      "text_a": "مغز من بر قلب من حاکم است.",
      "text_b": "قلب من بر مغز من حاکم است.",
      "dimension_mapping": {
        "a": "T",
        "b": "F"
      }
    },
    {
      "id": 24,
      "text_a": "معمولاً در کارهای روزانه مایلم بر حسب ضرورت‌ها و فوریت‌هایی که پیش می‌آید عمل کنم.",
      "text_b": "معمولاً در کارهای روزانه مایلم که طبق برنامه عمل کنم.",
      "dimension_mapping": {
        "a": "P",
        "b": "J"
      }
    },
    {
      "id": 25,
      "text_a": "از احساسات و عواطف درونی خود کمتر با دیگران صحبت می‌کنم.",
      "text_b": "افکار و عواطف خود را آزاد و راحت بیان می‌کنم.",
      "dimension_mapping": {
        "a": "I",
        "b": "E"
      }
    },
    {
      "id": 26,
      "text_a": "کلمه مشخص و دقیق",
      "text_b": "کلمه تمثیلی و کنایه‌ای",
      "dimension_mapping": {
        "a": "S",
        "b": "N"
      }
    },
    {
      "id": 27,
      "text_a": "آدم منصف",
      "text_b": "آدم قدردان",
      "dimension_mapping": {
        "a": "T",
        "b": "F"
      }
    },
    {
      "id": 28,
      "text_a": "معمولاً کارها را شروع می‌کنم و در حین اجرا به رفع مشکلات پیش آمده می‌پردازم.",
      "text_b": "معمولاً قبل از شروع کارها مقدمات کار را آماده و مشکلات را پیش‌بینی می‌کنم.",
      "dimension_mapping": {
        "a": "P",
        "b": "J"
      }
    },
    {
      "id": 29,
      "text_a": "کارهای فردی",
      "text_b": "کارهای گروهی",
      "dimension_mapping": {
        "a": "I",
        "b": "E"
      }
    },
    {
      "id": 30,
      "text_a": "واقعیات (آنچه که هست) و پدیده‌ها",
      "text_b": "حقایق (آنچه که باید باشد) و ایده‌ها",
      "dimension_mapping": {
        "a": "S",
        "b": "N"
      }
    },
    {
      "id": 31,
      "text_a": "عدل و انصاف",
      "text_b": "بذل و بخشش",
      "dimension_mapping": {
        "a": "T",
        "b": "F"
      }
    },
    {
      "id": 32,
      "text_a": "تهیه فهرست از کارهایی که باید در روز تعطیل انجام داد را کاری بیهوده و عبث می‌دانم.",
      "text_b": "تهیه فهرست از کارهایی که باید در روز تعطیل انجام داد را کاری جدی و سودمند می‌دانم.",
      "dimension_mapping": {
        "a": "P",
        "b": "J"
      }
    },
    {
      "id": 33,
      "text_a": "معمولاً در مهمانی‌ها و مجالس با شخص یا اشخاصی که از قبل می‌شناسم گفتگو می‌کنم.",
      "text_b": "معمولاً در مهمانی‌ها و مجالس به دنبال اشخاص جدیدی هستم تا با آنها گفتگو کرده و آشنا شوم.",
      "dimension_mapping": {
        "a": "I",
        "b": "E"
      }
    },
    {
      "id": 34,
      "text_a": "دوستان من اکثراً واقع‌گرا و واقع‌بین هستند.",
      "text_b": "دوستان من اکثراً کسانی هستند که قوه تخیل قوی دارند.",
      "dimension_mapping": {
        "a": "S",
        "b": "N"
      }
    },
    {
      "id": 35,
      "text_a": "فردی که با دلایل و استدلال با موضوعات برخورد می‌کند، بهتر است.",
      "text_b": "فردی که با عاطفه و احساس واقعی و دلسوزی با موضوعات برخورد می‌کند، بهتر است.",
      "dimension_mapping": {
        "a": "T",
        "b": "F"
      }
    },
    {
      "id": 36,
      "text_a": "غالباً خود را ملزم به انجام کارها سر وقت معین و مشخص ندانسته و خود را در محدوده زمان مقید نمی‌کنم.",
      "text_b": "غالباً برنامه خود را بطور مشخص و دقیق تعیین کرده و بر انجام آنها در سر وقت مقرر اصرار می‌ورزم.",
      "dimension_mapping": {
        "a": "P",
        "b": "J"
      }
    },
    {
      "id": 37,
      "text_a": "آرام و کم صدا",
      "text_b": "با نشاط و فعال",
      "dimension_mapping": {
        "a": "I",
        "b": "E"
      }
    },
    {
      "id": 38,
      "text_a": "دوست دارم فردی واقع‌گرا و دقیق باشم.",
      "text_b": "دوست دارم فردی مبتکر و خلاق باشم.",
      "dimension_mapping": {
        "a": "S",
        "b": "N"
      }
    },
    {
      "id": 39,
      "text_a": "به تجزیه و تحلیل موضوعات علاقه دارم.",
      "text_b": "به فیلم‌ها و بحث‌های عاطفی که به مسائل انسانی می‌پردازند، علاقه دارم.",
      "dimension_mapping": {
        "a": "T",
        "b": "F"
      }
    },
    {
      "id": 40,
      "text_a": "معمولاً زندگی خود را با توجه به اوضاع و احوالی که پیش می‌آید، تنظیم و اداره می‌کنم.",
      "text_b": "معمولاً کارهایی را که مایل به انجام آن هستم یادداشت کرده یا حداقل به طور مرتب به خاطر می‌سپارم.",
      "dimension_mapping": {
        "a": "P",
        "b": "J"
      }
    },
    {
      "id": 41,
      "text_a": "کم حرف",
      "text_b": "خوش صحبت",
      "dimension_mapping": {
        "a": "I",
        "b": "E"
      }
    },
    {
      "id": 42,
      "text_a": "عینیت",
      "text_b": "ذهنیت",
      "dimension_mapping": {
        "a": "S",
        "b": "N"
      }
    },
    {
      "id": 43,
      "text_a": "دوست دارم فردی باشم متفکر، که عاقلانه رفتار می‌کند.",
      "text_b": "دوست دارم فردی باشم عاطفی، که با احساسات انسانی رفتار می‌کند.",
      "dimension_mapping": {
        "a": "T",
        "b": "F"
      }
    },
    {
      "id": 44,
      "text_a": "بعضی افراد مرا آدمی بی‌نظم و دارای زندگی شلوغ می‌دانند.",
      "text_b": "بعضی افراد مرا آدمی متوقع و غیر قابل انعطاف می‌دانند.",
      "dimension_mapping": {
        "a": "P",
        "b": "J"
      }
    },
    {
      "id": 45,
      "text_a": "پس از مکث و تأمل کافی، نسبت به بحث یا سوالات مطرح شده اظهار نظر می‌کنم.",
      "text_b": "در هر لحظه که فرصت شد سوالات را مطرح یا نظر خود را اعلام می‌کنم.",
      "dimension_mapping": {
        "a": "I",
        "b": "E"
      }
    },
    {
      "id": 46,
      "text_a": "ثبات و استحکام",
      "text_b": "تغییر و انعطاف",
      "dimension_mapping": {
        "a": "S",
        "b": "N"
      }
    },
    {
      "id": 47,
      "text_a": "بیشتر از نتیجه‌گیری‌های منطقی و استدلال استفاده می‌کنم.",
      "text_b": "بیشتر بر اساس عواطف و عقاید شخصی نسبت به زندگی یا افراد عمل می‌کنم.",
      "dimension_mapping": {
        "a": "T",
        "b": "F"
      }
    },
    {
      "id": 48,
      "text_a": "هر وقت که مناسب بود و فرصت دست داد نسبت به انجام کارها آزادانه و بدون فشار اقدام می‌کنم.",
      "text_b": "این مهم است که از قبل بدانم چه کاری یا چه چیزی از من انتظار دارند تا به انجام آنها بپردازم.",
      "dimension_mapping": {
        "a": "P",
        "b": "J"
      }
    },
    {
      "id": 49,
      "text_a": "ترجیح می‌دهم در جمع افراد توسط فرد دیگری معرفی شوم.",
      "text_b": "معمولاً در جمع افراد دیگران را به یکدیگر معرفی می‌کنم.",
      "dimension_mapping": {
        "a": "I",
        "b": "E"
      }
    },
    {
      "id": 50,
      "text_a": "تلاش می‌کنم با رعایت ترتیب مراحل پیش‌بینی شده کارها را انجام دهم.",
      "text_b": "هنگام انجام دادن کارها از قسمت‌های بی‌اهمیت آن صرف‌نظر کنم.",
      "dimension_mapping": {
        "a": "S",
        "b": "N"
      }
    },
    {
      "id": 51,
      "text_a": "نسبت به هر گروه یا افراد سازمانی که با آنها کار می‌کنم، بر اساس تجزیه و تحلیل دقیق اوضاع و اطلاعات موجود اظهار نظر می‌کنم.",
      "text_b": "نسبت به هر گروه یا افراد سازمانی که با آنها کار می‌کنم، بر اساس درک نیازهایشان عواطف انسانی و خود را به جای آنها گذاشتن اظهار نظر می‌کنم.",
      "dimension_mapping": {
        "a": "T",
        "b": "F"
      }
    },
    {
      "id": 52,
      "text_a": "معمولاً بدون فوت وقت یک کار یا پروژه را شروع و به هر قسمتی از آن که ممکن باشد زودتر می‌پردازم.",
      "text_b": "معمولاً در انجام کارها آنها را به اجزای مشخص تقسیم کرده و سپس به ترتیب به انجام بخش‌های مشخص شده می‌پردازم.",
      "dimension_mapping": {
        "a": "P",
        "b": "J"
      }
    },
    {
      "id": 53,
      "text_a": "به کارهای فردی (یا حداکثر با یکی دو نفر دیگر) علاقه مندم.",
      "text_b": "به کارهای گروهی علاقه مندم.",
      "dimension_mapping": {
        "a": "I",
        "b": "E"
      }
    },
    {
      "id": 54,
      "text_a": "یکی از اشکالات اساسی زندگی من یکنواختی و چسبیدن به برنامه و کار مشخص بوده است.",
      "text_b": "یکی از اشکالات اساسی زندگی من از شاخه‌ای به شاخه ای دیگر پریدن و داشتن برنامه‌های متعدد بوده است.",
      "dimension_mapping": {
        "a": "S",
        "b": "N"
      }
    },
    {
      "id": 55,
      "text_a": "قاطع بودن",
      "text_b": "ملایم بودن",
      "dimension_mapping": {
        "a": "T",
        "b": "F"
      }
    },
    {
      "id": 56,
      "text_a": "علاقه مندم جلسات و گردهمایی‌ها هنگامی شروع شود که همگی افراد حضور و آمادگی لازم را داشته و احساس راحتی کنند.",
      "text_b": "علاقه مندم که جلسات رأس ساعت مقرر شروع شود و روی وقت‌شناسی تأکید دارم.",
      "dimension_mapping": {
        "a": "P",
        "b": "J"
      }
    },
    {
      "id": 57,
      "text_a": "از نظر دیگران ممکن است فردی منزوی و گوشه‌گیر به نظر برسم.",
      "text_b": "از نظر دیگران ممکن است فردی پرحرف و سطحی به نظر برسم.",
      "dimension_mapping": {
        "a": "I",
        "b": "E"
      }
    },
    {
      "id": 58,
      "text_a": "کارها را با نظم و ترتیب و مرحله به مرحله انجام می‌دهم.",
      "text_b": "قسمت‌های مهم و جالب کار را زودتر انجام می‌دهم.",
      "dimension_mapping": {
        "a": "S",
        "b": "N"
      }
    },
    {
      "id": 59,
      "text_a": "اصول و حق",
      "text_b": "گذشت و مهربانی",
      "dimension_mapping": {
        "a": "T",
        "b": "F"
      }
    },
    {
      "id": 60,
      "text_a": "مقید بودن به برنامه‌ای که از قبل مشخص شده باشد برای من جالب نیست.",
      "text_b": "از انجام دادن کارهایی که از قبل مشخص شده باشد، احساس رضایت دارم.",
      "dimension_mapping": {
        "a": "P",
        "b": "J"
      }
    }
  ],
  "scoring": {
    "method": "برای هر یک از چهار بعد، تعداد پاسخ‌هایی را که به هر قطب (مثلاً E در مقابل I) اشاره دارد، بشمارید.",
    "instructions": "به ازای هر پاسخ، یک نمره به ستون مربوط به آن گزینه تعلق می‌گیرد. در پایان، نمرات هر ستون جمع زده می‌شود. بالاترین نمره در هر جفت از گرایش‌ها (مثلاً درون‌گرایی در مقابل برون‌گرایی)، تیپ شخصیتی فرد را در آن بعد مشخص می‌کند.",
    "notes": "این ابزار صرفاً تیپ‌های شخصیتی را شناسایی می‌کند و جنبه تشخیصی و بیماری‌شناسی ندارد، زیرا همه تیپ‌ها ارزشمند هستند و هیچ‌کدام بر دیگری برتری ندارد."
  },
  "question_map": [
    { "id": 1, "a": "I", "b": "E" }, { "id": 2, "a": "S", "b": "N" }, { "id": 3, "a": "T", "b": "F" }, { "id": 4, "a": "P", "b": "J" },
    { "id": 5, "a": "I", "b": "E" }, { "id": 6, "a": "S", "b": "N" }, { "id": 7, "a": "T", "b": "F" }, { "id": 8, "a": "P", "b": "J" },
    { "id": 9, "a": "I", "b": "E" }, { "id": 10, "a": "S", "b": "N" }, { "id": 11, "a": "T", "b": "F" }, { "id": 12, "a": "P", "b": "J" },
    { "id": 13, "a": "I", "b": "E" }, { "id": 14, "a": "S", "b": "N" }, { "id": 15, "a": "T", "b": "F" }, { "id": 16, "a": "P", "b": "J" },
    { "id": 17, "a": "I", "b": "E" }, { "id": 18, "a": "S", "b": "N" }, { "id": 19, "a": "T", "b": "F" }, { "id": 20, "a": "P", "b": "J" },
    { "id": 21, "a": "I", "b": "E" }, { "id": 22, "a": "S", "b": "N" }, { "id": 23, "a": "T", "b": "F" }, { "id": 24, "a": "P", "b": "J" },
    { "id": 25, "a": "I", "b": "E" }, { "id": 26, "a": "S", "b": "N" }, { "id": 27, "a": "T", "b": "F" }, { "id": 28, "a": "P", "b": "J" },
    { "id": 29, "a": "I", "b": "E" }, { "id": 30, "a": "S", "b": "N" }, { "id": 31, "a": "T", "b": "F" }, { "id": 32, "a": "P", "b": "J" },
    { "id": 33, "a": "I", "b": "E" }, { "id": 34, "a": "S", "b": "N" }, { "id": 35, "a": "T", "b": "F" }, { "id": 36, "a": "P", "b": "J" },
    { "id": 37, "a": "I", "b": "E" }, { "id": 38, "a": "S", "b": "N" }, { "id": 39, "a": "T", "b": "F" }, { "id": 40, "a": "P", "b": "J" },
    { "id": 41, "a": "I", "b": "E" }, { "id": 42, "a": "S", "b": "N" }, { "id": 43, "a": "T", "b": "F" }, { "id": 44, "a": "P", "b": "J" },
    { "id": 45, "a": "I", "b": "E" }, { "id": 46, "a": "S", "b": "N" }, { "id": 47, "a": "T", "b": "F" }, { "id": 48, "a": "P", "b": "J" },
    { "id": 49, "a": "I", "b": "E" }, { "id": 50, "a": "S", "b": "N" }, { "id": 51, "a": "T", "b": "F" }, { "id": 52, "a": "P", "b": "J" },
    { "id": 53, "a": "I", "b": "E" }, { "id": 54, "a": "S", "b": "N" }, { "id": 55, "a": "T", "b": "F" }, { "id": 56, "a": "P", "b": "J" },
    { "id": 57, "a": "I", "b": "E" }, { "id": 58, "a": "S", "b": "N" }, { "id": 59, "a": "T", "b": "F" }, { "id": 60, "a": "P", "b": "J" }
  ],
  "interpretation": {
    "dimension_details": [
      {
        "category": "منبع و جهت انرژی",
        "types": [
          {
            "name": "درون‌گرا (Introvert - I)",
            "description": "افرادی که درون‌گرایی را ترجیح می‌دهند، تمایل دارند روی تجربیات و عقاید دنیای درونی خود تمرکز کنند و از افکار، احساسات و اندیشه‌های درونی خود انرژی می‌گیرند.",
            "characteristics": [
              "کشش به سمت دنیای درونی خویش",
              "تمایل به برقراری ارتباط نوشتاری",
              "یادگیری بهتر با تامل و تمرین فکری",
              "علایق عمیق دارند",
              "تمایل به اندیشه و تفکر پیش از هرگونه حرف یا عمل",
              "تودار بودن و محرمانه عمل کردن",
              "در خود فرو رفته و اغلب کمرو",
              "غالباً ساکت و منزوی و متمایل به کارهای فردی"
            ]
          },
          {
            "name": "برون‌گرا (Extravert - E)",
            "description": "افرادی که برون‌گرایی را ترجیح می‌دهند، تمایل دارند بر دنیای بیرونی و افراد و رویدادهای خارجی تمرکز کنند و از رویدادها، تجربه‌ها و تعاملات بیرونی انرژی می‌گیرند.",
            "characteristics": [
              "تمایل و توجه به محیط خارج",
              "تمایل به برقراری ارتباط کلامی",
              "یادگیری بهتر از طریق کار عملی و یا بحث و گفتگو",
              "گستردگی تعاملات اجتماعی",
              "تمایل به صحبت و واکنش پیش از هرگونه تفکر و تامل",
              "اجتماعی بودن و داشتن رفتارهای معنی‌دار",
              "پیش قدم در کار و فعالیت و ایجاد روابط"
            ]
          }
        ]
      },
      {
        "category": "نحوه دریافت اطلاعات",
        "types": [
          {
            "name": "حسی (Sensing - S)",
            "description": "افرادی که ترجیح می‌دهند با استفاده از حواس پنج‌گانه به آنچه در اطرافشان می‌گذرد پی ببرند و به حقایق عملی یک موقعیت توجه می‌کنند.",
            "characteristics": [
              "تمرکز بر هر آنچه که واقعیت دارد",
              "اعتماد به تجربه",
              "خواستار دریافت اطلاعات جز به جز و گام به گام",
              "ارزش دادن به کار عملی",
              "مشاهده و یادآوری مکرر",
              "توجه به زمان حال"
            ]
          },
          {
            "name": "شهودی (Intuiting - N)",
            "description": "افرادی که ترجیح می‌دهند با دیدن تصویر بزرگ و تمرکز بر پیوندها و ارتباطات میان حقایق، اطلاعات را درک کنند و در دیدن امکانات جدید و خلاقیت بینش خوبی دارند.",
            "characteristics": [
              "دیدگاه وسیع",
              "اهمیت دادن به بینش تخیلی",
              "طرفدار استدلال نظری و غیر عملی",
              "راهنمای آینده و اعتماد به الهامات قلبی",
              "از این شاخه به آن شاخه پریدن"
            ]
          }
        ]
      },
      {
        "category": "نحوه تصمیم‌گیری و قضاوت",
        "types": [
          {
            "name": "تفکری (Thinking - T)",
            "description": "افرادی که در تصمیم‌گیری به نتایج منطقی انتخاب یا عمل توجه دارند و بی‌طرفانه و به شکل عینی، علت و معلول را تجزیه و تحلیل می‌کنند.",
            "characteristics": [
              "داشتن نگرش تحلیلی نسبت به وقایع",
              "حل منطقی مسائل",
              "استفاده از دلایل علت و معلولی",
              "سرسختی",
              "تلاش برای دستیابی به حقیقت غیر فردی و واقعی",
              "منطقی و منصف بودن",
              "مغزشان بر قلبشان حاکم است"
            ]
          },
          {
            "name": "احساسی (Feeling - F)",
            "description": "افرادی که به احساسات دیگران توجه می‌کنند، نیازها و ارزش‌ها را درک کرده و احساساتشان را نشان می‌دهند.",
            "characteristics": [
              "افرادی با عاطفه و احساساتی هستند",
              "در تصمیم‌گیری به آنچه دل بر آن گواهی می‌دهد عمل می‌کنند",
              "ملایم، با گذشت و مهربان هستند",
              "فشارهای وارد بر دیگران را ارزیابی می‌کنند",
              "زودرنج هستند",
              "قلب آنها بر مغزشان حاکم است"
            ]
          }
        ]
      },
      {
        "category": "سبک زندگی و برخورد با جهان خارج",
        "types": [
          {
            "name": "منضبط (Judging - J)",
            "description": "این افراد سبک زندگی ساختاری و سازمان‌یافته دارند و دوست دارند هر چیزی در جای خود قرار گیرد.",
            "characteristics": [
              "برنامه خود را دقیق مشخص کرده و بر انجام آن در سروقت پافشاری می‌کنند",
              "طرفدار قاعده و قانون هستند",
              "برای جلوگیری از فراموشی، کارها را یادداشت می‌کنند",
              "به نظم و ترتیب و برنامه خیلی اهمیت می‌دهند"
            ]
          },
          {
            "name": "ملاحظه‌کار (Perceiving - P)",
            "description": "این افراد انطباق‌پذیر و انعطاف‌پذیر هستند و زندگی خود را با توجه به شرایطی که پیش می‌آید، تنظیم و اداره می‌کنند.",
            "characteristics": [
              "طرفدار زور و اجبار نیستند",
              "خود را ملزم به انجام کارها در سروقت مشخص نمی‌دانند",
              "در کارهای پیش‌بینی نشده یا نیازمند واکنش فوری موفق هستند",
              "دوست دارند کارها آزاد و قابل تغییر باشد",
              "با فشارهای آخرین لحظه احساس انرژی می‌کنند"
            ]
          }
        ]
      }
    ],
    "personality_types_16": [
      { "type": "ISTJ", "description": "جدی، آرام، واقع‌گرا، منظم و منطقی. موفقیت را با تمرکز و پشتکار بدست می‌آورد. مسئولیت‌پذیر است و کارها را بدون توجه به معطلی انجام می‌دهد." },
      { "type": "ISFJ", "description": "آرام، خوش‌برخورد، مسئولیت‌پذیر و وظیفه‌شناس. برای انجام وظایف خالصانه کار می‌کند. دقیق، زحمت‌کش، وفادار و نسبت به احساسات دیگران بسیار حساس است." },
      { "type": "INFJ", "description": "موفقیت را با پشتکار فراوان بدست می‌آورد و در انجام کارها اشتیاق دارد. آرام، با قدرت و وظیفه‌شناس است. به کمک به دیگران علاقه دارد و مورد احترام مردم است." },
      { "type": "INTJ", "description": "افکاری بدیع و مبتکرانه دارد و پرانرژی است. قدرت خاصی در سازماندهی کارها دارد و می‌تواند کارها را با کمک یا بدون کمک دیگران به پایان برساند. منتقد، مستقل، مصمم و گاهی لجوج است." },
      { "type": "ISTP", "description": "افرادی با نگاه نافذ، آرام و محتاط که زندگی را با کنجکاوی تجزیه و تحلیل می‌کنند. علاقه‌مند به اصول علمی، علت و معلول و موضوعات فنی هستند." },
      { "type": "ISFP", "description": "خستگی‌ناپذیر، خوش‌برخورد، حساس و کم‌ادعا در مورد توانایی‌های خود. از مخالفت پرهیز می‌کند و ارزش‌های خود را به دیگران تحمیل نمی‌کند. اغلب دنباله‌روی وفاداری است و از زمان حال لذت می‌برد." },
      { "type": "INFP", "description": "پر از وفاداری و هواخواهی پرحرارت. علاقه فراوانی به یادگیری، ایده‌های جدید و زبان دارد. گاهی بیش از حد مسئولیت قبول می‌کند و آن را به پایان می‌رساند." },
      { "type": "INTP", "description": "آرام و تودار. در آزمون‌های آموزشی بخصوص در زمینه علمی و تئوری موفق است. به ایده‌ها و نظریات جدید علاقه نشان می‌دهد و به محافل اجتماعی یا بحث‌های بیهوده توجهی ندارد." },
      { "type": "ESTP", "description": "واقع‌گرا و بندرت نگران می‌شود. از هرچه پیش آید لذت می‌برد. به ورزش و موضوعات فنی علاقه نشان می‌دهد و در محافل مختلف شرکت می‌کند." },
      { "type": "ESFP", "description": "برون‌گرا، زودجوش، مهمان‌نواز و خوش‌برخورد. علاقه زیادی به لذت بردن از زمان حال دارد. به ورزش و تولید و ساخت علاقه دارد و برای حقایق اهمیت بیشتری نسبت به تئوری‌های پیچیده قائل است." },
      { "type": "ENFP", "description": "پر حرارت، پرانرژی، دارای قوه تخیل بالا و مبتکر. توانایی انجام هر کاری که به آن علاقه‌مند است را دارد. در پیدا کردن راه‌حل برای هر مشکلی سریع عمل می‌کند و آماده کمک به دیگران است." },
      { "type": "ENTP", "description": "صریح، بی‌ریا، پرهیجان، پرحرف و باهوش. در پیدا کردن راه‌حل‌های مبتکرانه برای موضوعات پیچیده مهارت دارد. از انجام کارهای یکنواخت روزانه سرباز می‌زند." },
      { "type": "ESTJ", "description": "واقع‌بین، قاطع و کم‌احساس. در زمینه تجارت و کارهای فنی استعداد خاصی از خود نشان می‌دهد. به سازماندهی و هدایت فعالیت‌ها و پروژه‌ها علاقه دارد." },
      { "type": "ESFJ", "description": "خوش‌قلب، خوش‌صحبت، محبوب و مسئولیت‌پذیر. از سنین پایین مشارکت و همکاری با دیگران را به خوبی یاد می‌گیرد. همیشه می‌خواهد یک کار نیک برای دیگران انجام دهد و نیاز به تشویق و قدردانی دارد." },
      { "type": "ENFJ", "description": "مسئولیت‌پذیر و دلسوز. حساسیت واقعی نسبت به آنچه دیگران می‌خواهند، فکر می‌کنند و دارند. در ارائه یک موضوع یا رهبری یک بحث گروهی توانایی خاصی دارد. زودجوش، محبوب و فعال در امور آموزشی است." },
      { "type": "ENTJ", "description": "پرنشاط، صادق و موفق در مطالعات و آموزش تحصیلی. قدرت رهبری در فعالیت‌های مختلف دارد. معمولاً در کارهایی که نیاز به منطق زیاد و بیان هوشیارانه دارد موفق است." }
    ]
  }
}